wikibasemigrator/__init__.py
wikibasemigrator/cli.py
wikibasemigrator/config.py
wikibasemigrator/exceptions.py
wikibasemigrator/mapper.py
wikibasemigrator/merger.py
wikibasemigrator/migrator.py
wikibasemigrator/qsgenerator.py
wikibasemigrator/wikibase.py
wikibasemigrator/model/__init__.py
wikibasemigrator/model/datatypes.py
wikibasemigrator/model/migration_mark.py
wikibasemigrator/model/profile.py
wikibasemigrator/model/quickstatements.py
wikibasemigrator/model/translations.py
wikibasemigrator/profiles/FactGrid.yaml
wikibasemigrator/profiles/WikibaseMigrationTest.yaml
wikibasemigrator/profiles/__init__.py
wikibasemigrator/profiles/base_template.yaml
wikibasemigrator/profiles/test.yaml
wikibasemigrator/resources/Commons_to_Wikidata_QuickStatements.svg
wikibasemigrator/resources/logo.png
wikibasemigrator/resources/logo.svg
wikibasemigrator/resources/logo_square.png
wikibasemigrator/web/__init__.py
wikibasemigrator/web/config_page.py
wikibasemigrator/web/docker_main.py
wikibasemigrator/web/item_selectors.py
wikibasemigrator/web/main.py
wikibasemigrator/web/migration_view.py
wikibasemigrator/web/oauth.py
wikibasemigrator/web/selection_view.py
wikibasemigrator/web/translation_view.py
wikibasemigrator/web/webpage.py
wikibasemigrator/web/webserver.py
wikibasemigrator/web/wikibase_controller_page.py
wikibasemigrator/web/components/__init__.py
wikibasemigrator/web/components/code.py
wikibasemigrator/web/components/log_handler.py
wikibasemigrator/web/components/progress.py
wikibasemigrator/web/components/wikibase_item.js
wikibasemigrator/web/components/wikibase_item.py
wikibasemigrator-0.0.20.dist-info/METADATA
wikibasemigrator-0.0.20.dist-info/WHEEL
wikibasemigrator-0.0.20.dist-info/entry_points.txt
wikibasemigrator-0.0.20.dist-info/licenses/LICENSE
wikibasemigrator-0.0.20.dist-info/RECORD
