Metadata-Version: 2.4
Name: wikibasemigrator
Version: 0.0.20
Dynamic: Summary
Project-URL: Home, https://github.com/tholzheim/WikibaseMigrator
Project-URL: Documentation, https://github.com/tholzheim/WikibaseMigrator
Project-URL: Source, https://github.com/tholzheim/WikibaseMigrator
Project-URL: Issues, https://github.com/tholzheim/WikibaseMigrator/issues
Author-email: Tim Holzheim <tim.holzheim@rwth-aachen.de>
Maintainer-email: Tim Holzheim <tim.holzheim@rwth-aachen.de>
License-Expression: Apache-2.0
License-File: LICENSE
Classifier: Development Status :: 4 - Beta
Classifier: Intended Audience :: Developers
Classifier: Intended Audience :: Education
Classifier: Intended Audience :: Science/Research
Classifier: License :: OSI Approved :: Apache Software License
Classifier: Operating System :: OS Independent
Classifier: Programming Language :: Python :: 3 :: Only
Classifier: Programming Language :: Python :: 3.10
Classifier: Programming Language :: Python :: 3.11
Classifier: Programming Language :: Python :: 3.12
Classifier: Programming Language :: Python :: 3.13
Classifier: Topic :: Software Development :: Libraries :: Python Modules
Requires-Python: >=3.10
Requires-Dist: authlib
Requires-Dist: nicegui
Requires-Dist: pandas
Requires-Dist: pydantic
Requires-Dist: pygments
Requires-Dist: python-dateutil
Requires-Dist: pyyaml
Requires-Dist: quickstatements-client
Requires-Dist: sparqlwrapper
Requires-Dist: typer
Requires-Dist: wikibaseintegrator>=0.12.8
Provides-Extra: test
Requires-Dist: deepdiff; extra == 'test'
Requires-Dist: mypy; extra == 'test'
Requires-Dist: pytest; extra == 'test'
Requires-Dist: pytest-asyncio; extra == 'test'
Requires-Dist: pytest-cov; extra == 'test'
Requires-Dist: ruff; extra == 'test'
Requires-Dist: tox; extra == 'test'
